fastapi_sdk/__init__.py
fastapi_sdk/controllers/__init__.py
fastapi_sdk/controllers/mixin.py
fastapi_sdk/controllers/model.py
fastapi_sdk/controllers/route.py
fastapi_sdk/middleware/auth.py
fastapi_sdk/middleware/secure.py
fastapi_sdk/security/oauth.py
fastapi_sdk/security/permissions.py
fastapi_sdk/security/webhook.py
fastapi_sdk/utils/constants.py
fastapi_sdk/utils/dependencies.py
fastapi_sdk/utils/exception_handler.py
fastapi_sdk/utils/model.py
fastapi_sdk/utils/response.py
fastapi_sdk/utils/schema.py
fastapi_sdk/utils/test.py
fastapi_sdk/webhook/generator.py
fastapi_sdk/webhook/handler.py
fastapi_sdk/webhook/route.py
fastapi_sdk-0.12.3.dist-info/licenses/LICENSE
fastapi_sdk-0.12.3.dist-info/METADATA
fastapi_sdk-0.12.3.dist-info/WHEEL
fastapi_sdk-0.12.3.dist-info/top_level.txt
fastapi_sdk-0.12.3.dist-info/RECORD
