Metadata-Version: 2.4
Name: fastapi-sdk
Version: 0.12.3
Summary: Utilities for FastAPI projects.
Requires-Python: >=3.12
License-File: LICENSE
Requires-Dist: authlib>=1.5.1
Requires-Dist: fastapi[standard]==0.128
Requires-Dist: odmantic>=1.0.2
Requires-Dist: pydantic>=2.10.6
Requires-Dist: pydantic-settings>=2.8.1
Requires-Dist: pytest>=8.3.5
Requires-Dist: pytest-asyncio>=0.25.3
Requires-Dist: requests>=2.32.3
Requires-Dist: shortuuid>=1.0.13
Requires-Dist: starlette==0.50
Dynamic: license-file
